a2aflow/__init__.py
a2aflow/client.py
a2aflow/core.py
a2aflow/main.py
a2aflow/models.py
a2aflow/server.py
a2aflow/tasks.py
a2aflow/utils.py
a2aflow/adapters/__init__.py
a2aflow/utils/__init__.py
a2aflow-0.1.1.dist-info/METADATA
a2aflow-0.1.1.dist-info/WHEEL
a2aflow-0.1.1.dist-info/licenses/LICENSE
a2aflow-0.1.1.dist-info/RECORD
