Metadata-Version: 2.4
Name: a2aflow
Version: 0.1.1
Summary: A lightweight bridge between PocketFlow and the Agent2Agent protocol
Project-URL: Homepage, https://github.com/your-username/A2AFlow
Project-URL: Bug Tracker, https://github.com/your-username/A2AFlow/issues
Project-URL: Documentation, https://your-username.github.io/A2AFlow
Author-email: Sean Kruzel <sean@closedloop.tech>
License: MIT License
License-File: LICENSE
Keywords: a2a,agent,agent2agent,llm,pocketflow
Classifier: Development Status :: 3 - Alpha
Classifier: Intended Audience :: Developers
Classifier: License :: OSI Approved :: MIT License
Classifier: Programming Language :: Python :: 3
Classifier: Programming Language :: Python :: 3.9
Classifier: Programming Language :: Python :: 3.10
Classifier: Programming Language :: Python :: 3.11
Classifier: Programming Language :: Python :: 3.12
Classifier: Topic :: Scientific/Engineering :: Artificial Intelligence
Requires-Python: >=3.9
Requires-Dist: fastapi>=0.115.12
Requires-Dist: httpx-sse>=0.4.0
Requires-Dist: httpx>=0.28.1
Requires-Dist: pocketflow>=0.0.1
Requires-Dist: pydantic>=2.11.3
Requires-Dist: pyjwt>=2.10.1
Requires-Dist: requests>=2.32.3
Requires-Dist: starlette>=0.46.1
Requires-Dist: twine>=6.1.0
Requires-Dist: uvicorn>=0.34.0
